onesait_platform_jupyter4/__init__.py
onesait_platform_jupyter4/_version.py
onesait_platform_jupyter4-0.1.0.data/data/share/jupyter/labextensions/onesait_platform_jupyter4/build_log.json
onesait_platform_jupyter4-0.1.0.data/data/share/jupyter/labextensions/onesait_platform_jupyter4/package.json
onesait_platform_jupyter4-0.1.0.data/data/share/jupyter/labextensions/onesait_platform_jupyter4/schemas/onesait_platform_jupyter4/package.json.orig
onesait_platform_jupyter4-0.1.0.data/data/share/jupyter/labextensions/onesait_platform_jupyter4/schemas/onesait_platform_jupyter4/plugin.json
onesait_platform_jupyter4-0.1.0.data/data/share/jupyter/labextensions/onesait_platform_jupyter4/static/lib_index_js.515242cd68a93a318e25.js
onesait_platform_jupyter4-0.1.0.data/data/share/jupyter/labextensions/onesait_platform_jupyter4/static/lib_index_js.515242cd68a93a318e25.js.map
onesait_platform_jupyter4-0.1.0.data/data/share/jupyter/labextensions/onesait_platform_jupyter4/static/remoteEntry.6108fb4bd59ccb56ee66.js
onesait_platform_jupyter4-0.1.0.data/data/share/jupyter/labextensions/onesait_platform_jupyter4/static/remoteEntry.6108fb4bd59ccb56ee66.js.map
onesait_platform_jupyter4-0.1.0.data/data/share/jupyter/labextensions/onesait_platform_jupyter4/static/style.js
onesait_platform_jupyter4-0.1.0.data/data/share/jupyter/labextensions/onesait_platform_jupyter4/static/style_index_js.a5b9646729bd9759d848.js
onesait_platform_jupyter4-0.1.0.data/data/share/jupyter/labextensions/onesait_platform_jupyter4/static/style_index_js.a5b9646729bd9759d848.js.map
onesait_platform_jupyter4-0.1.0.data/data/share/jupyter/labextensions/onesait_platform_jupyter4/install.json
onesait_platform_jupyter4-0.1.0.dist-info/METADATA
onesait_platform_jupyter4-0.1.0.dist-info/WHEEL
onesait_platform_jupyter4-0.1.0.dist-info/licenses/LICENSE
onesait_platform_jupyter4-0.1.0.dist-info/RECORD
